README.txt
setup.py
pr_am/__init__.py
pr_am/__main__.py
pr_am.egg-info/PKG-INFO
pr_am.egg-info/SOURCES.txt
pr_am.egg-info/dependency_links.txt
pr_am.egg-info/entry_points.txt
pr_am.egg-info/requires.txt
pr_am.egg-info/top_level.txt