Metadata-Version: 1.0
Name: pr-am
Version: 1.0.11
Summary: Project Reality (BF2) Artillery Map
Home-page: UNKNOWN
Author: Xembie
Author-email: xembot@gmail.com
License: MIT
Keywords: battlefield bf2 artillery map projectreality pr
Platform: UNKNOWN
